{"x'activetru": 2, "x'ascend": 177, "x'delay": 348, "x'drive": 519, "x'eventtru": 690, "x'highth": 864, "x'i": 1036, "x'imag": 1300, "x'instanc": 1469, "x'last": 1641, "x'leftth": 1811, "x'lengthx'high": 1983, "x'low": 2161, "x'lowth": 2330, "x'path": 2501, "x'quiet": 2670, "x'rangeth": 2841, "x'revers": 3014, "x'rightth": 3186, "x'simpl": 3359, "x'stabl": 3529, "x'transact": 3700, "xaaab": 3874, "xabber": 4044, "xaddress": 4312, "xadl": 4484, "xaducntv": 6317, "xae": 6490, "xah": 6739, "xah'": 7974, "xai": 8239, "xaidpoj": 8488, "xaixysvuk": 8659, "xanadu": 8833, "xanthipp": 10182, "xapewf": 10436, "xarchscript": 10607, "xauthor": 10784, "xaver": 10955, "xax": 11124, "xba": 11580, "xbawqh": 11748, "xbbgd": 11919, "xbfa": 12088, "xbgknaxmdu": 12256, "xbiepvtmrxhdbobamdifxo": 12431, "xbjag": 12618, "xbm": 12788, "xbmybudgensu": 13151, "xbngytznunrslgujga": 13328, "xbooktitl": 13510, "xbox": 13685, "xboyex": 16118, "xbp": 16289, "xbrym": 19509, "xbt": 19679, "xbtf": 19944, "xbwspblob": 20113, "xbyt": 20285, "xca": 20452, "xcap": 20912, "xcap'": 21280, "xcat": 21547, "xcay": 22499, "xcbdwl": 22668, "xcbuildconfigur": 22839, "xcc": 23023, "xccawtcto": 23288, "xcccccccc": 23462, "xcconfigurationlist": 23635, "xcd": 23822, "xcdfxrzkcrpi": 23990, "xcen": 24167, "xcf": 24336, "xchang": 24881, "xci": 25349, "xcirca": 25517, "xcj": 25688, "xcji": 25856, "xcjoqbk": 26024, "xckre": 26195, "xckznvx": 26364, "xckzvfa": 26536, "xclanguagespecificationidentifi": 26708, "xclwq": 26905, "xcmd": 27073, "xco": 27339, "xcode": 27507, "xcode'": 83205, "xcodeproj": 83472, "xcolor": 83988, "xcon": 84159, "xconq": 84328, "xcount": 84496, "xcqx": 84668, "xcr": 84837, "xcrossbc": 85004, "xcrosscd": 85177, "xcrossdb": 85350, "xcrossref": 85523, "xcscheme": 85697, "xcshareddata": 85949, "xcxyezlihgfidmgxuv": 86287, "xcyecfbbpx": 86470, "xda": 86645, "xdalkaccoxomumdmkcnqbndo": 86912, "xdd": 87100, "xdel": 87268, "xdelet": 87436, "xdim": 87802, "xdnndc": 87970, "xdoanex": 88141, "xdoi": 88412, "xdotwb": 88681, "xdqihetoaul": 88852, "xdqrzrtajyvng": 89028, "xdr": 89206, "xdxa": 89555, "xecxl": 89724, "xeditor": 89894, "xee": 90261, "xefo": 90527, "xej": 90695, "xekrl": 90863, "xelatex": 91033, "xemac": 91400, "xen": 91768, "xena": 92523, "xenix": 92891, "xenofon": 93164, "xenon": 93335, "xenopu": 93706, "xensummit": 98515, "xent": 98687, "xentt": 98951, "xeon": 99318, "xeotxchdwrzw": 99974, "xeprxeueaaovjl": 100151, "xeqcwtctgkrvyoqigjgaa": 100330, "xeqkipkamcbcybnqicf": 100516, "xerox": 100700, "xerox'": 122796, "xerx": 123459, "xetex": 123826, "xeujtxp": 124191, "xevjngum": 124363, "xezvy": 124536, "xfa": 124706, "xfc": 125269, "xfcn": 125804, "xfcqmbtnaa": 125973, "xfcwrr": 126147, "xfdl": 126318, "xfdpatuhiostc": 126487, "xfe": 126665, "xfedstrzlmw": 127026, "xff": 127202, "xffc": 129387, "xfff": 129554, "xffff": 129819, "xffffc": 130184, "xffffffff": 130356, "xfg": 132197, "xfgadz": 132365, "xfig": 132536, "xfile": 132704, "xform": 134662, "xfpgugekafeai": 135029, "xfrx": 135205, "xfur": 135374, "xfvyrgom": 135543, "xfxkznrpoic": 135716, "xgaussian": 135892, "xgbdzlm": 136066, "xgidetcjjftxi": 136238, "xgj": 136416, "xgjjhx": 136583, "xgl": 136752, "xgncbkhevft": 136919, "xgowo": 137095, "xgq": 137265, "xgr": 137433, "xgroduz": 137699, "xgrsdb": 137869, "xgu": 138038, "xguard": 138402, "xgur": 138671, "xgv": 138840, "xgx": 139008, "xgyybsn": 139176, "xhandl": 139347, "xhg": 139517, "xhi": 139684, "xhifmg": 139852, "xhihk": 140023, "xhikuzpbjat": 140193, "xhimgq": 140369, "xhiq": 140540, "xhjqhhomfzjil": 140709, "xhkflojd": 140885, "xhmfsxhiiad": 141058, "xhoi": 141234, "xhotouhpbxp": 141403, "xhoxjit": 141579, "xhqfwzx": 141751, "xhtml": 141923, "xhtwfeypqbbkiuyemd": 145148, "xhusbjwbhgibam": 145331, "xhvcssmhdjqplailhhmaqwa": 145510, "xhx": 145697, "xia": 157969, "xian": 159297, "xiang": 160253, "xiangd": 162978, "xiangen": 163149, "xianghong": 163515, "xianghua": 163866, "xiangmin": 165305, "xiangwen": 166067, "xiangyi": 166240, "xiangyu": 166412, "xiangzh": 167078, "xianp": 167250, "xianzheng": 168007, "xiao": 168180, "xiaobin": 174714, "xiaochen": 174982, "xiaochun": 175448, "xiaofan": 176210, "xiaogang": 176874, "xiaohui": 177245, "xiaohuixi": 202495, "xiaolu": 202769, "xiaomi": 202940, "xiaomin": 203507, "xiaop": 204263, "xiaoru": 204629, "xiaorun": 204800, "xiaosong": 204972, "xiaowei": 205639, "xiaoxi": 206101, "xiaoxiang": 206272, "xiaoxiao": 206445, "xiaoxuan": 206617, "xiaoxun": 206789, "xiaoyan": 207253, "xiaoyu": 207425, "xiaozhu": 208187, "xiarmando": 208555, "xico": 208920, "xid": 209577, "xie": 210896, "xie'": 242074, "xif": 242438, "xihxznw": 242606, "xii": 242778, "xiii": 243627, "xije": 244655, "xikui": 244823, "xikuiw": 287321, "xile": 327165, "xilingz": 327334, "xilinx": 329844, "xilocblob": 330592, "xime": 330764, "ximkrctxfo": 331229, "xin": 331404, "xinan": 337826, "xing": 337995, "xingbo": 354907, "xinghao": 355273, "xinglonb": 355445, "xingwei": 359277, "xingyou": 359449, "xinlinp": 359621, "xinru": 359790, "xintens": 361320, "xinu": 361591, "xinv": 361759, "xinyun": 361928, "xiong": 362099, "xioo": 370715, "xiorjp": 370883, "xip": 371054, "xipe": 371220, "xisbn": 371777, "xisnpxilscp": 371946, "xit": 372122, "xiu": 373271, "xiujuan": 373538, "xiunan": 374198, "xiuyang": 374367, "xiv": 374539, "xiwen": 375373, "xiwp": 375641, "xix": 375810, "xiy": 376663, "xiz": 376831, "xizi": 377392, "xjdfjn": 377561, "xjf": 377732, "xjgzfo": 377900, "xjhf": 378070, "xjhk": 378239, "xjicrivvbdsgmpi": 378408, "xjj": 378588, "xjjd": 378755, "xjlntwrw": 378924, "xjmuabnchgbuapbmei": 379097, "xjnwkrosli": 379280, "xjryqq": 379455, "xjsfv": 379626, "xjvyvrerrihz": 379796, "xjz": 379973, "xjzea": 380141, "xkappzw": 380311, "xkaqlkrvcwriwclh": 380482, "xkcd": 380663, "xkegi": 381222, "xkeox": 381388, "xkeypoint": 381556, "xkfwdzvqvnhtaamdomnr": 381829, "xkkvuqhw": 382013, "xkleg": 382186, "xkng": 382356, "xknizz": 382525, "xkqfyvlp": 382696, "xkr": 382869, "xktqojhzdfjo": 383332, "xkwv": 383509, "xkyohwe": 383678, "xlab": 383850, "xlabel": 385272, "xlak": 385833, "xlakub": 386001, "xlakzni": 386172, "xlbvcfcda": 386343, "xldb": 386516, "xlg": 386685, "xlgrxnhaeymmugicvdwefoyomfhunb": 386852, "xlgzhcn": 387045, "xlim": 387217, "xlink": 388166, "xlinkit": 388532, "xlint": 388802, "xljjhpff": 388971, "xlncit": 389144, "xlocat": 389315, "xlsm": 389485, "xlsreadwrit": 390147, "xltar": 390614, "xlxghqhlowp": 390784, "xma": 390959, "xmax": 392762, "xmbytgvusbl": 393028, "xmc": 393204, "xmcjex": 393372, "xmdmnzpkfudgk": 393543, "xmean": 393721, "xmen": 394187, "xmfvfe": 394455, "xmhg": 394625, "xmhioj": 394793, "xmin": 394963, "xming": 395229, "xmkdir": 395397, "xml": 396044, "xml'": 651324, "xmlbean": 652590, "xmldecl": 652866, "xmlentiti": 653137, "xmlfilenam": 653411, "xmlio": 653586, "xmln": 654047, "xmlschema": 660898, "xmlstart": 666247, "xmltext": 666523, "xmlurl": 666798, "xmmbyc": 666966, "xmodel": 667137, "xmp": 667307, "xmqlslwflqndd": 667573, "xmv": 667749, "xmvaqx": 667917, "xmvhoazlqb": 668086, "xmwlmxxg": 668260, "xmxn": 668433, "xna": 668600, "xnbattb": 668961, "xnd": 669133, "xng": 669300, "xnhlt": 669467, "xnksspukto": 669637, "xnoc": 669812, "xnor": 669981, "xnq": 670543, "xntnk": 670711, "xnv": 670881, "xnzbf": 671048, "xnzskn": 671216, "xoabnnn": 671386, "xof": 671558, "xojr": 671920, "xoki": 672089, "xomhz": 672258, "xomino": 672428, "xoom": 672695, "xor": 673258, "xore": 677148, "xori": 677316, "xoro": 677585, "xov": 678341, "xovzaz": 678509, "xpafemp": 678679, "xpage": 678851, "xpath": 679101, "xpch": 679471, "xpg": 679640, "xpgjftfai": 680203, "xpiqpcga": 680375, "xplore": 680548, "xplormath": 681996, "xpmbercaot": 682465, "xpo": 682638, "xpointer": 686762, "xpose": 686935, "xposit": 687204, "xpoynqsvhng": 687569, "xpress": 687745, "xprobe": 688210, "xpublish": 688381, "xpuilcyzo": 688553, "xpw": 688727, "xpyi": 688992, "xqa": 689161, "xqcba": 689329, "xqcdak": 689499, "xqdara": 689670, "xqdzro": 689841, "xqefr": 690012, "xqhuurarytqtq": 690180, "xqk": 690358, "xqkxrniwhz": 690525, "xqmbfpc": 690699, "xqt": 690871, "xquartz": 691039, "xqueri": 691308, "xqwkcmkxskvxhljjdhgzxnyukfvga": 692367, "xqxxfl": 692561, "xqyrw": 692732, "xqz": 692902, "xra": 693069, "xrang": 693237, "xraysgi": 693405, "xref": 693674, "xrefin": 695301, "xrefmz": 695472, "xrep": 695643, "xresolut": 695812, "xrg": 696563, "xri": 696730, "xrixqfdmup": 696998, "xrmi": 697173, "xrmtn": 697342, "xrovjjrhboo": 697512, "xrowjjnkdpmrc": 697688, "xrqzwhvac": 697866, "xrvzqziftyzlfouoi": 698040, "xrx": 698221, "xrz": 698388, "xrze": 698555, "xsbqyehwutem": 698724, "xsbrklgnuzp": 698901, "xscale": 699077, "xscq": 700119, "xscslpkybk": 700286, "xsd": 700461, "xsdvbab": 705805, "xsede": 705976, "xseed": 706146, "xselwryl": 706314, "xseri": 706487, "xset": 706656, "xsgv": 706824, "xsi": 706993, "xsinnscxi": 712277, "xskvj": 712451, "xsl": 712621, "xslt": 713283, "xsot": 717759, "xstar": 717928, "xstd": 718194, "xstringifi": 718460, "xsub": 719124, "xswgsa": 719293, "xswit": 719464, "xswq": 719634, "xsyr": 719802, "xsyxn": 719971, "xsz": 720141, "xtaxu": 720309, "xtend": 720479, "xtest": 720748, "xth": 722274, "xthreshold": 722536, "xti": 722810, "xticklabel": 723271, "xtild": 723444, "xtildeinv": 723712, "xtjhbh": 723886, "xtm": 724057, "xtouchlednotif": 724225, "xtoy": 724501, "xtra": 724668, "xtraterr": 725135, "xtreme": 725308, "xtro": 725579, "xtrue": 725847, "xtsarjkzhzwvlkzwwv": 726314, "xtshtzda": 726497, "xttgv": 726670, "xtune": 726840, "xtv": 728358, "xtvcymgbdek": 728526, "xtvm": 728702, "xtyw": 728870, "xtzpxrawfh": 729037, "xu'": 729212, "xuaalqtm": 729376, "xuaijna": 729547, "xuan": 729718, "xuciyvapjl": 744657, "xuctfx": 744832, "xue": 745003, "xufmenvdh": 745762, "xuik": 745936, "xuivmxq": 746105, "xukatytr": 746277, "xul": 746450, "xuncqox": 746617, "xurl": 746789, "xuthi": 746959, "xuyang": 747129, "xvalu": 747300, "xvb": 747864, "xvdmrye": 748031, "xvf": 748202, "xvhyrm": 753429, "xvhzkrbti": 753600, "xvi": 753774, "xvii": 754628, "xviii": 755283, "xvjiku": 755842, "xvm": 756013, "xvnw": 756181, "xvoo": 756350, "xvq": 756519, "xvrubh": 756686, "xvsrnlong": 756856, "xvtjztqoccttaxhr": 757027, "xvvdvlfbhlq": 757208, "xvvrpdriw": 757384, "xvw": 757558, "xvx": 757725, "xvzlliwbukiqmcw": 757893, "xwati": 758071, "xwbfwbvh": 758239, "xwc": 758412, "xwcz": 758580, "xwe": 758750, "xwehm": 758918, "xwfeab": 759088, "xwgj": 759259, "xwhether": 759427, "xwk": 759699, "xwqp": 759867, "xwr": 760035, "xwu": 760203, "xwuh": 760371, "xwxia": 760540, "xx'": 760709, "xxb": 760875, "xxcdo": 761042, "xxcgrcz": 761212, "xxcl": 761384, "xxgnjx": 761553, "xxii": 761724, "xxj": 762188, "xxjbkqve": 762356, "xxmnb": 762529, "xxnaiydfwchg": 762699, "xxspec": 762876, "xxsrv": 763148, "xxsvr": 763619, "xxt": 764083, "xxtgnw": 764251, "xxth": 764422, "xxuan": 764690, "xxukwr": 764858, "xxup": 765029, "xxuskuonhg": 765198, "xxvn": 765373, "xxvrg": 765542, "xxwz": 765712, "xxx": 765881, "xxxai": 784513, "xxxii": 784681, "xxxtra": 784950, "xxxvi": 785218, "xxxvii": 785487, "xxxx": 785757, "xxxxlet'": 791545, "xxxxx": 791716, "xxxxxx": 793944, "xxxxxxxxx": 796180, "xxxxxxxxxx": 796353, "xxymhwadgao": 796527, "xxz": 796703, "xxzvyqxk": 796871, "xy'": 797044, "xybbn": 797208, "xybino": 797378, "xybpstpdg": 797549, "xyg": 797723, "xyipccm": 797891, "xykdc": 798063, "xykezh": 798232, "xykzfxbxnntvh": 798401, "xylophon": 798579, "xyoe": 798849, "xyr": 799018, "xytho": 799185, "xyysiytfvhlxwavsoaf": 800136, "xyz": 800320, "xyzgraph": 837279, "xyzq": 837450, "xyzx": 837619, "xzcmqrrtniawnyvctoxn": 837883, "xzf": 838068, "xzgm": 838334, "xzibit": 838503, "xzl": 838773, "xzsgcpvpkk": 838941, "xzvf": 839116, "xzz": 839480, "x'rang": 839648, "xalan": 840014, "xanth": 840285, "xar": 840751, "xargument": 841019, "xavera": 841292, "xavier": 841462, "xavor": 847799, "xbar": 847967, "xbc": 848328, "xboolean": 848494, "xcb": 848666, "xce": 848929, "xcfilter": 849192, "xchar": 849462, "xcite": 849632, "xcolormapev": 850188, "xcontent": 850364, "xcoord": 850535, "xcrun": 850705, "xcuserdata": 850873, "xcworkspac": 851046, "xcz": 851219, "xdata": 851482, "xdef": 851746, "xdefthm": 852012, "xebar": 852281, "xeroc": 852449, "xextern": 852716, "xfer": 852888, "xffffff": 853057, "xffffffffffffffff": 853228, "xfffffffful": 853410, "xfirst": 853585, "xfx": 853754, "xgmml": 854017, "xgradient": 854186, "xi'an": 854359, "xiangqi": 854723, "xiangxu": 854894, "xiankang": 855165, "xiaobo": 855526, "xiaofeng": 855695, "xiaohong": 857239, "xiaojuan": 857608, "xiaoli": 858068, "xiaom": 859781, "xiaominl": 860336, "xiaon": 860508, "xiaoqiu": 860876, "xiaoyi": 861048, "xib": 861610, "xibo": 861873, "xifc": 862041, "xifcb": 862305, "xifl": 862570, "xifm": 862834, "xifu": 863098, "xigui": 863362, "xiipt": 863531, "xingdong": 863799, "xinlu": 863972, "xinninggui": 864141, "xinput": 864313, "xint": 864484, "xinteg": 864653, "xinyi": 864824, "xipt": 865190, "xistrat": 865358, "xivpt": 865529, "xlayer": 865797, "xlib": 865966, "xliii": 866234, "xlsx": 866403, "xlvii": 869372, "xmajorgrid": 869541, "xmatalb": 869908, "xmodem": 870080, "xmosaic": 870250, "xmpe": 870422, "xmulat": 870591, "xnet": 870760, "xnon": 870928, "xnxm": 871097, "xob": 871264, "xoe": 871527, "xofb": 871790, "xofe": 872054, "xor'": 872318, "xora": 872486, "xoz": 872654, "xpa": 872822, "xpect": 874269, "xpoint": 874437, "xproof": 874607, "xpt": 874876, "xpublic": 875043, "xputc": 875215, "xpz": 875385, "xqbwx": 875846, "xrandr": 876015, "xrefentri": 876185, "xrefpq": 876361, "xresolu": 876533, "xrvne": 876703, "xsat": 876872, "xscalar": 877039, "xsect": 877211, "xseer": 877478, "xss": 877747, "xta": 878105, "xteam": 878368, "xtick": 878832, "xtitlenot": 879196, "xtk": 879468, "xtz": 879833, "xv'": 880294, "xval": 880462, "xvar": 881117, "xvec": 881383, "xvh": 881549, "xviipt": 881716, "xvlarray": 881985, "xwamdasb": 882158, "xwindow": 882316, "xwindowattribut": 882685, "xxedwindagreatxx": 882865, "xxi": 883042, "xxooc": 883503, "xxpt": 883970, "xxv": 884237, "xxvpt": 884404, "xxxxxxx": 884672, "xxxxxxxx": 884842, "xxxxxxxxxxxxxxxxxxxxxxxxxxxxxxxxxxxxxxxxxxxxxxxxxxxxxxxxxxxxxx": 885111, "xxxyy": 885339, "xxyx": 885507, "xyb": 885676, "xyo": 885843, "xyx": 886011, "xyxb": 886179, "xyzr": 886347, "xyzzi": 886516, "xzi": 886785, "xab": 887048, "xacayygjpedk": 889947, "xadd": 890223, "xade": 890787, "xadisk": 890956, "xaf": 891129, "xage": 891377, "xajil": 891545, "xak": 891716, "xalansampl": 891983, "xalanservlet": 892160, "xan": 892337, "xanda": 892800, "xanot": 893465, "xanthin": 893636, "xanthinuria": 894005, "xanthomatosi": 894279, "xaoc": 894652, "xap": 894822, "xapool": 895087, "xarg": 895260, "xauth": 895521, "xav": 895691, "xaxa": 895957, "xbaaaaaelftksuqmcc": 896128, "xbasej": 896408, "xbean": 896580, "xbglxtovxhluiujpl": 896756, "xbi": 897035, "xbrain": 897205, "xbyekyvfsm": 897375, "xcavat": 897647, "xcaxffeujxkac": 898111, "xceller": 898386, "xchfilu": 899515, "xcigadxqmfbnadoyrhh": 899784, "xclose": 900065, "xcluder": 900237, "xcmi": 900410, "xcsde": 900584, "xcsf": 900754, "xdamra": 900923, "xdb": 901191, "xdbm": 901361, "xde": 901534, "xdg": 901897, "xdh": 902164, "xdie": 902528, "xdir": 902794, "xdmail": 902961, "xdoc": 903132, "xdoclet": 903304, "xdrivehttpmanag": 903482, "xdriveunit": 903663, "xdsh": 903840, "xdt": 904106, "xea": 904276, "xebia": 904443, "xebialab": 904616, "xebium": 904793, "xecur": 904965, "xenapi": 905135, "xenc": 905306, "xendou": 905475, "xenobiot": 905743, "xenocanto": 906310, "xep": 906486, "xepgujwbjdunqcalmrl": 906654, "xerc": 906935, "xercesimpl": 907108, "xercesjarv": 907286, "xercessampl": 907462, "xerial": 907640, "xerjyjghpzygt": 907815, "xerjyjmlv": 908092, "xertsjjnrfz": 908363, "xeustechnolog": 908636, "xew": 908816, "xfce": 908985, "xffd": 909254, "xfh": 909421, "xfire": 909688, "xflbbevksaaaaaelftksuqmcc": 909864, "xfpanel": 910151, "xfpkelmm": 910325, "xfrancv": 910595, "xftp": 910766, "xfvz": 910933, "xghire": 911102, "xgo": 911370, "xhar": 911637, "xhbqaaacbjsfjnaab": 911808, "xhd": 912090, "xhtmlrender": 912355, "xhwokoukbnfrrkgislevwabsig": 912532, "xhxielab": 912820, "xiadi": 914275, "xiangxin": 914445, "xiantong": 916479, "xianyang": 916652, "xiap": 916923, "xidtech": 918078, "xihong": 918641, "ximelagatran": 918812, "xinbtao": 919086, "xingp": 919256, "xinlei": 919426, "xirp": 919596, "xisemel": 919765, "xist": 919938, "xiuy": 921587, "xjavadoc": 922047, "xjc": 922222, "xjcplugin": 922396, "xjdf": 922574, "xjdflib": 922743, "xjhn": 922915, "xjsf": 923181, "xjujgsp": 923351, "xkfnt": 923620, "xkid": 923887, "xkpx": 924151, "xkrx": 924417, "xkwcx": 924683, "xlator": 924950, "xlet": 925123, "xlf": 925294, "xlightweb": 925559, "xljwhbvgjttonljzrlhw": 925737, "xlkfaiivihv": 926019, "xlo": 926294, "xlob": 926559, "xlr": 926728, "xlseasi": 928078, "xlson": 928252, "xmaant": 928423, "xmabootrt": 928596, "xmacom": 928772, "xmapack": 928945, "xmartclient": 929119, "xmartserv": 929299, "xmemcach": 929477, "xmexhp": 929653, "xmi": 929921, "xmlbuilder": 930386, "xmlc": 930563, "xmlconf": 930735, "xmlconfig": 930908, "xmldb": 931085, "xmldoclet": 931257, "xmldsig": 931431, "xmleditor": 931605, "xmlenc": 931782, "xmlfactori": 931955, "xmlfilter": 932132, "xmlfresh": 932309, "xmlgraphic": 932483, "xmlhttprequest": 932661, "xmlmap": 932844, "xmlmatcher": 933017, "xmlmerger": 933192, "xmlmime": 933367, "xmlmind": 933539, "xmlp": 933711, "xmlparser": 933881, "xmlparserapi": 934059, "xmlpersist": 934237, "xmlpolici": 934413, "xmlpublic": 934588, "xmlpull": 934764, "xmlqueri": 934938, "xmlresolv": 935112, "xmlresourc": 935286, "xmlresum": 935461, "xmlrpc": 935634, "xmlsec": 935810, "xmlsecur": 935983, "xmlsoap": 936160, "xmlstore": 936333, "xmlstringpars": 936507, "xmlstub": 936686, "xmltool": 936858, "xmltype": 937034, "xmltypeoracl": 937207, "xmlui": 937386, "xmlunit": 937757, "xmlutil": 937931, "xmlworker": 938104, "xmlwrapper": 938279, "xmlwriter": 938456, "xmlzen": 938631, "xmpp": 938803, "xmyqaaaaasuvork": 939071, "xnc": 939350, "xnfqxmjozmtoznc": 939517, "xnio": 939796, "xniqaaaabjru": 939969, "xnjdygtgyaakiyu": 940243, "xoc": 940520, "xolit": 940785, "xom": 940957, "xop": 941128, "xopioidr": 941296, "xpand": 941567, "xpars": 941737, "xpathapi": 941908, "xpather": 942082, "xpc": 942254, "xpdl": 943699, "xpgi": 943869, "xpgn": 944137, "xpgradsup": 944405, "xpl": 944677, "xpmazxyklp": 944846, "xpmjmzbpigpgizsbcwcandzbriz": 945118, "xpnpep": 945407, "xpom": 946770, "xpot": 946939, "xpotp": 949374, "xpp": 949543, "xpr": 949714, "xqnyrjk": 951851, "xradar": 952122, "xrcc": 952295, "xre": 955532, "xreceptor": 955897, "xremot": 956169, "xreport": 956342, "xrn": 956515, "xrodrmpgmntb": 959944, "xrodrmpgmntd": 960219, "xrodrmpgmntg": 960494, "xrra": 960769, "xrt": 961429, "xrtnhw": 961600, "xsbt": 961868, "xsddoc": 962041, "xsdlib": 962214, "xshell": 962388, "xsite": 962560, "xslp": 962733, "xslservlet": 962904, "xsltal": 963080, "xslthl": 963251, "xsltmp": 963423, "xsmpnqi": 963596, "xsoaaaaasuvork": 963865, "xsocket": 964141, "xsom": 964317, "xsp": 964487, "xsparql": 964656, "xspec": 964829, "xsraiaco": 964999, "xsraiacq": 965269, "xsrmc": 965541, "xst": 965810, "xstore": 966078, "xstream": 966249, "xstreamfx": 966425, "xtag": 966601, "xtalbg": 966772, "xtbd": 967042, "xterm": 967308, "xtestfil": 967477, "xtesturl": 967650, "xtext": 967823, "xtiff": 967996, "xtinv": 968167, "xtjkv": 968336, "xtkvica": 968603, "xtn": 968872, "xtodhonkm": 969335, "xtqllghtcosarkmpvfa": 969606, "xtrp": 969887, "xuanl": 970153, "xudavidson": 972238, "xuey": 972512, "xuhua": 972681, "xukggaddrv": 972948, "xume": 973220, "xunit": 973389, "xupdat": 973563, "xuunivers": 973734, "xux": 973908, "xuxi": 974175, "xuxjsahn": 974344, "xuzha": 974614, "xvcj": 974782, "xvfz": 975050, "xvnc": 975318, "xvp": 975488, "xvqxswem": 975755, "xvyiq": 976025, "xwf": 976294, "xwiki": 976559, "xwmcaiebq": 976733, "xwork": 977004, "xxbac": 977177, "xxiii": 977346, "xxl": 977613, "xxxfl": 977880, "xxylt": 978147, "xye": 978611, "xyggi": 978876, "xylb": 979242, "xylo": 979806, "xylos": 980164, "xylt": 980629, "xylulos": 981790, "xypron": 982059, "xzazjlvz": 982231, "xzg": 982501, "xaa": 982766, "xacml": 983014, "xantha": 983182, "xantha'": 983353, "xantham": 983525, "xanthan": 983697, "xanthat": 983868, "xanthate'": 984039, "xanthe'": 984213, "xanthein": 984385, "xanthein'": 984557, "xanthen": 984731, "xanthene'": 984902, "xanthian": 985076, "xanthic": 985249, "xanthin'": 985421, "xanthine'": 985594, "xanthippe'": 985768, "xanthium": 985943, "xanthochro": 986116, "xanthochroi": 986290, "xanthochroi'": 986466, "xanthochroia": 986643, "xanthochroid": 986820, "xanthochroism'": 986996, "xanthochromia": 987175, "xanthoma": 987353, "xanthoma'": 987525, "xanthomat": 987699, "xanthomata": 987873, "xanthomatos": 988048, "xanthomelan": 988224, "xanthon": 988400, "xanthophyl": 988571, "xanthophyll'": 988747, "xanthopsia": 988924, "xanthopterin": 989099, "xanthou": 989276, "xanthoura": 989448, "xanthoura'": 989622, "xanthoxyl": 989797, "xanthoxylum": 989971, "xanthoxylum'": 990147, "xanthu": 990324, "xanthus'": 990495, "xantippe'": 990668, "xavier'": 990842, "xaviera": 991014, "xaviera'": 991186, "xavler": 991359, "xavler'": 991530, "xbffffe": 991702, "xbfffffcc": 991874, "xbfffffd": 992049, "xbfffffdc": 992222, "xbfffffe": 992396, "xbfffffec": 992568, "xbfffffed": 992742, "xbffffff": 992917, "xbffffffc": 993090, "xdm": 993263, "xdock": 993431, "xdunypseideqiswqetlep": 993599, "xe'": 993783, "xebec": 993951, "xebec'": 994120, "xeclips": 994291, "xeeu": 994460, "xema": 994629, "xema'": 994798, "xemacs'": 994968, "xena'": 995140, "xenaki": 995310, "xenakis'": 995481, "xenarthr": 995654, "xenarthra": 995827, "xenarthra'": 996001, "xenia": 996176, "xenia'": 996638, "xenial": 996808, "xenic": 996979, "xenium": 997149, "xeno": 997320, "xeno'": 997488, "xenocr": 997658, "xenocrates'": 997829, "xenocryst": 998005, "xenocryst'": 998178, "xenodiagnos": 998353, "xenodiagnosi": 998529, "xenodiagnosis'": 998706, "xenodiagnost": 998885, "xenodochium": 999062, "xenogami": 999237, "xenogamy'": 999409, "xenogen": 999583, "xenogenes": 999754, "xenogenesi": 999928, "xenogenesis'": 1000103, "xenogenet": 1000280, "xenogeni": 1000454, "xenoglossia": 1000626, "xenoglossia'": 1000802, "xenograft": 1000979, "xenolith": 1001152, "xenolith'": 1001324, "xenomania": 1001498, "xenomorph": 1001672, "xenon'": 1001846, "xenophan": 1002017, "xenophanes'": 1002190, "xenophil": 1002366, "xenophile'": 1002540, "xenophilia": 1002715, "xenophob": 1002889, "xenophobe'": 1003063, "xenophobi": 1003238, "xenophobia": 1003412, "xenophobia'": 1003586, "xenophon": 1003762, "xenophon'": 1003935, "xenophya": 1004109, "xenoplast": 1004282, "xenopus": 1004456, "xenopus'": 1004628, "xenotim": 1004801, "xenotranspl": 1004973, "xenotransplant": 1005148, "xenotrop": 1005326, "xenurin": 1005499, "xenuru": 1005671, "xenurus'": 1005842, "xer": 1006015, "xerafin": 1006183, "xeransi": 1006354, "xerant": 1006526, "xeranthemum": 1006697, "xeraphin": 1006872, "xerarch": 1007044, "xerasia": 1007216, "xere": 1007388, "xeres'": 1007557, "xeric": 1007728, "xeriscap": 1007899, "xerochasi": 1008071, "xeroderm": 1008245, "xeroderma": 1008418, "xeroderma'": 1008591, "xerodermat": 1008766, "xerodermata": 1008940, "xerodermia": 1009116, "xerograph": 1009290, "xerographi": 1009465, "xerography'": 1009639, "xeroma": 1009815, "xeromata": 1009985, "xeromorph": 1010158, "xerophagi": 1010333, "xerophagy'": 1010507, "xerophil": 1010682, "xerophili": 1010854, "xerophthalm": 1011027, "xerophthalmia": 1011203, "xerophthalmia'": 1011380, "xerophyt": 1011559, "xerophyte'": 1011733, "xerophytism'": 1011908, "xeroradiographi": 1012085, "xeros": 1012264, "xeroser": 1012434, "xerosere'": 1012605, "xerosi": 1012779, "xerosis'": 1012950, "xerostoma": 1013123, "xerostomia": 1013297, "xerot": 1013471, "xerotherm": 1013640, "xerotripsi": 1013814, "xeru": 1013989, "xerus": 1014158, "xerxes'": 1014328, "xever": 1014500, "xever'": 1014670, "xfi": 1014841, "xfiniti": 1015008, "xfz": 1015178, "xhft": 1015345, "xhosa": 1015512, "xhosa'": 1015681, "xhosan": 1015852, "xhosan'": 1016023, "xi'": 1016195, "xiamen": 1016363, "xiamen'": 1016534, "xiaobai": 1016706, "xiaomei": 1016878, "xiaoping'": 1017049, "xih": 1017223, "xikar": 1017390, "ximen": 1017558, "ximena": 1017728, "ximena'": 1017899, "ximenean": 1018071, "ximenean'": 1018244, "ximenes'": 1018418, "ximenez": 1018591, "ximenez'": 1018763, "xingu": 1018936, "xingu'": 1019106, "xinguang": 1019277, "xingyu": 1019547, "xinhasdog": 1019717, "xinmin": 1019889, "xiongnu": 1020059, "xiongnu'": 1020231, "xiphia": 1020404, "xiphias'": 1020575, "xiphihumerali": 1020748, "xiphihumeralis": 1020926, "xiphiida": 1021105, "xiphiidae'": 1021278, "xiphiplastr": 1021453, "xiphiplastron": 1021629, "xiphistern": 1021806, "xiphisterna": 1021981, "xiphisternum": 1022157, "xiphisternum'": 1022333, "xiphoid": 1022511, "xiphopag": 1022682, "xiphopagu": 1022854, "xiphopagus": 1023028, "xiphophyl": 1023203, "xiphosura": 1023377, "xiphosura'": 1023551, "xiphosuran": 1023726, "xiphosuran'": 1023900, "xiuwrtliwyjxentstyqgpohhwidqd": 1024076, "xizang": 1024268, "xizang'": 1024439, "xla": 1024611, "xli": 1024779, "xlx": 1024947, "xman": 1025114, "xmapper": 1025283, "xmark": 1025551, "xmas'": 1025721, "xmase": 1025891, "xmaximum": 1026061, "xminimum": 1026234, "xmltoscreen": 1026407, "xnti": 1026582, "xnty'": 1026751, "xoana": 1026921, "xoanon": 1027091, "xoanon'": 1027262, "xochipilli": 1027434, "xochipilli'": 1027609, "xosa": 1027785, "xperanto": 1027953, "xql": 1028126, "xqrl": 1028293, "xqse": 1028462, "xqyvpfnzhwsmtsdv": 1028631, "xrd": 1028810, "xrycqwmpjfibuelh": 1029075, "xsdm": 1029254, "xsoft": 1029423, "xt'": 1029592, "xuanj": 1029760, "xuanm": 1029930, "xuewen": 1030098, "xuthu": 1030269, "xuthus'": 1030439, "xuzhou": 1030611, "xuzhou'": 1030782, "xview": 1030954, "xxdm": 1031123, "xylan": 1031292, "xylan'": 1031461, "xylem": 1031632, "xylem'": 1031801, "xylen": 1031972, "xylene'": 1032141, "xylenol": 1032313, "xylfwiuj": 1032484, "xylia": 1032655, "xylia'": 1032825, "xylic": 1032996, "xylidin": 1033166, "xylidine'": 1033339, "xylina": 1033513, "xylina'": 1033684, "xylitol": 1033856, "xylobalsamum": 1034027, "xylocain": 1034204, "xylocarp": 1034376, "xylocarp'": 1034548, "xylochrom": 1034722, "xylogen": 1034896, "xylograph": 1035067, "xylograph'": 1035241, "xylographer'": 1035416, "xylographi": 1035593, "xylography'": 1035767, "xyloid": 1035943, "xyloidin": 1036114, "xylol": 1036286, "xylol'": 1036552, "xylolog": 1036723, "xyloma": 1036895, "xylomata": 1037065, "xylomet": 1037238, "xylon": 1037409, "xylon'": 1037578, "xylonit": 1037749, "xylonite'": 1037921, "xylophag": 1038095, "xylophaga": 1038267, "xylophaga'": 1038441, "xylophagan": 1038616, "xylophage'": 1038790, "xylophil": 1038965, "xylophone'": 1039138, "xylophonist": 1039313, "xylopia": 1039488, "xylopia'": 1039660, "xylopyrographi": 1039833, "xylorimba": 1040012, "xylose'": 1040185, "xylotom": 1040357, "xylotomi": 1040529, "xylotomist": 1040701, "xylotomist'": 1040875, "xylotomy'": 1041051, "xylotypograph": 1041225, "xylotypographi": 1041403, "xylyl": 1041582, "xylyl'": 1041751, "xymen": 1041922, "xymenes'": 1042092, "xyplot": 1042265, "xyri": 1042435, "xyridac": 1042604, "xyridacea": 1042776, "xyridaceae'": 1042950, "xyridal": 1043126, "xyridales'": 1043298, "xyris'": 1043473, "xyst": 1043644, "xyst'": 1043812, "xyster": 1043982, "xyster'": 1044152, "xysti": 1044324, "xysto": 1044494, "xystoi": 1044664, "xystu": 1044835, "xystus": 1045005, "xyxi": 1045176, "xyzvl": 1045344, "xzagysvw": 1045513, "xac": 1045684, "xacc": 1045834, "xad": 1046002, "xag": 1046152, "xampl": 1046302, "xanga": 1047531, "xat": 1047697, "xbdzunumw": 1047863, "xbeam": 1048034, "xbf": 1048202, "xcapb": 1048365, "xclvqcdtbm": 1048726, "xcw": 1048898, "xdatas": 1049060, "xdeadbeef": 1049725, "xdelta": 1050193, "xdigit": 1050364, "xebjmiyduxq": 1050534, "xed": 1050707, "xegvi": 1051067, "xeih": 1051236, "xeinoub": 1051402, "xentrix": 1051666, "xeoq": 1051931, "xfqyhqsin": 1052291, "xfvco": 1052462, "xfvr": 1052629, "xgk": 1055477, "xgrid": 1055640, "xgvo": 1055809, "xgyro": 1055975, "xhayman": 1056144, "xhersch": 1056314, "xhpz": 1056484, "xhrh": 1056844, "xhrwx": 1057298, "xhypo": 1057659, "xiangbo": 1057828, "xiangxiang": 1058000, "xiangyao": 1058173, "xiangyj": 1058835, "xianm": 1059106, "xiaohuihobb": 1059554, "xiaohuihuman": 1059731, "xiaoj": 1059908, "xiaojian": 1060077, "xiaojin": 1060249, "xiaoml": 1060615, "xiaoyong": 1060885, "xieaffili": 1061542, "xieprofessordegre": 1061716, "xieshuang": 1061898, "xifara": 1062072, "xikhynbnemurnolpbzsgzbctibkltc": 1062241, "xikuiend": 1066633, "xingdmv": 1066907, "xingmv": 1067080, "xingreli": 1067252, "xingsv": 1067425, "xingyao": 1067596, "xiniti": 1067766, "xinxin": 1067937, "xinxinz": 1068207, "xinyang": 1068478, "xiomara": 1068647, "xioyang": 1069013, "xisew": 1069671, "xiuzhen": 1075009, "xja": 1075477, "xjennif": 1075642, "xjtu": 1076009, "xjuchiwzqep": 1076176, "xjwagi": 1076543, "xkeystrok": 1076709, "xkeyxkfqcgdeqxvymja": 1076980, "xkeyxkfqcgdeqxvymjuzoti": 1077161, "xkeyxkfqcgdeqxvymtqxnzmzndi": 1077346, "xkeyxkfqcgdeqxvyndk": 1077537, "xkeyxkfqcgdeqxvyndq": 1077717, "xkeyxkfqcgdeqxvyndyymdk": 1077898, "xkeyxkfqcgdeqxvynjc": 1078084, "xkeyxkfqcgdeqxvynju": 1078265, "xkeyxkfqcgdeqxvynta": 1078445, "xkeyxkfqcgdeqxvyntc": 1078625, "xkeyxkfqcgdeqxvyntizotk": 1078806, "xkkwww": 1078991, "xksqmyuaiy": 1091697, "xlan": 1091869, "xle": 1092031, "xliu": 1092198, "xllang": 1094476, "xllangsan": 1094831, "xllangsi": 1094998, "xlm": 1095166, "xlpage": 1095333, "xlpageloc": 1096895, "xlpagetempl": 1097064, "xlsdv": 1097236, "xlwsfgzp": 1097588, "xmlandcast": 1101882, "xmlfile": 1102150, "xmlfooter": 1107872, "xmlheader": 1108135, "xmlpars": 1108398, "xmltutori": 1122710, "xmtc": 1133787, "xmx": 1133953, "xnffi": 1138500, "xnhu": 1146803, "xnqnbhrwb": 1149081, "xoal": 1165113, "xochitl": 1165279, "xoff": 1165645, "xog": 1165812, "xon": 1167705, "xooghium": 1167871, "xout": 1168136, "xow": 1168300, "xphase": 1168465, "xpixel": 1168635, "xquak": 1169000, "xque": 1169169, "xral": 1169833, "xrm": 1170095, "xroad": 1170262, "xsel": 1170432, "xsen": 1170601, "xshi": 1170769, "xsml": 1171037, "xspeed": 1171201, "xstab": 1171372, "xstatic": 1171540, "xsvx": 1171805, "xswang": 1172259, "xtal": 1172428, "xte": 1173087, "xthr": 1173628, "xtpxtpvkrxeci": 1173995, "xtr": 1174362, "xtractaur": 1174997, "xtrain": 1175270, "xttbar": 1175903, "xtunea": 1176073, "xukm": 1176243, "xum": 1176413, "xvmofum": 1176866, "xvzf": 1177035, "xwqo": 1177198, "xxxifcollidedwith": 1177364, "xxxifcollideswith": 1177546, "xxxv": 1177728, "xybar": 1177897, "xyear": 1178066, "xyuan": 1178235, "xyzabc": 1178404, "xyzefg": 1178574, "xyzfmt": 1178744, "xyzsessid": 1178910, "xzq": 1179268}